<?xml version="1.0" encoding="UTF-8"?>
<!DOCTYPE mapper PUBLIC "-//mybatis.org//DTD Mapper 3.0//EN" "http://mybatis.org/dtd/mybatis-3-mapper.dtd">
<mapper namespace="com.ccclubs.pub.orm.mapper.VerUpgradeMapper">
  <resultMap id="BaseResultMap" type="com.ccclubs.pub.orm.model.VerUpgrade">
    <!--
      WARNING - @mbg.generated
      This element is automatically generated by MyBatis Generator, do not modify.
    -->
    <id column="id" jdbcType="INTEGER" property="id" />
    <result column="soft_ver_id" jdbcType="INTEGER" property="softVerId" />
    <result column="hard_ver_id" jdbcType="INTEGER" property="hardVerId" />
    <result column="model_id" jdbcType="INTEGER" property="modelId" />
    <result column="tel_type" jdbcType="INTEGER" property="telType" />
    <result column="tel_model" jdbcType="VARCHAR" property="telModel" />
    <result column="inner_ver" jdbcType="VARCHAR" property="innerVer" />
    <result column="is_open" jdbcType="TINYINT" property="isOpen" />
    <result column="des" jdbcType="VARCHAR" property="des" />
    <result column="up_ver_no" jdbcType="VARCHAR" property="upVerNo" />
    <result column="ser_ftp_id" jdbcType="INTEGER" property="serFtpId" />
    <result column="per_timeout" jdbcType="INTEGER" property="perTimeout" />
    <result column="per_max_vehicle" jdbcType="INTEGER" property="perMaxVehicle" />
    <result column="file_name" jdbcType="VARCHAR" property="fileName" />
    <result column="turn_off_flag" jdbcType="TINYINT" property="turnOffFlag" />
  </resultMap>
  <sql id="Example_Where_Clause">
    <!--
      WARNING - @mbg.generated
      This element is automatically generated by MyBatis Generator, do not modify.
    -->
    <where>
      <foreach collection="oredCriteria" item="criteria" separator="or">
        <if test="criteria.valid">
          <trim prefix="(" prefixOverrides="and" suffix=")">
            <foreach collection="criteria.criteria" item="criterion">
              <choose>
                <when test="criterion.noValue">
                  and ${criterion.condition}
                </when>
                <when test="criterion.singleValue">
                  and ${criterion.condition} #{criterion.value}
                </when>
                <when test="criterion.betweenValue">
                  and ${criterion.condition} #{criterion.value} and #{criterion.secondValue}
                </when>
                <when test="criterion.listValue">
                  and ${criterion.condition}
                  <foreach close=")" collection="criterion.value" item="listItem" open="(" separator=",">
                    #{listItem}
                  </foreach>
                </when>
              </choose>
            </foreach>
          </trim>
        </if>
      </foreach>
    </where>
  </sql>
  <sql id="Update_By_Example_Where_Clause">
    <!--
      WARNING - @mbg.generated
      This element is automatically generated by MyBatis Generator, do not modify.
    -->
    <where>
      <foreach collection="example.oredCriteria" item="criteria" separator="or">
        <if test="criteria.valid">
          <trim prefix="(" prefixOverrides="and" suffix=")">
            <foreach collection="criteria.criteria" item="criterion">
              <choose>
                <when test="criterion.noValue">
                  and ${criterion.condition}
                </when>
                <when test="criterion.singleValue">
                  and ${criterion.condition} #{criterion.value}
                </when>
                <when test="criterion.betweenValue">
                  and ${criterion.condition} #{criterion.value} and #{criterion.secondValue}
                </when>
                <when test="criterion.listValue">
                  and ${criterion.condition}
                  <foreach close=")" collection="criterion.value" item="listItem" open="(" separator=",">
                    #{listItem}
                  </foreach>
                </when>
              </choose>
            </foreach>
          </trim>
        </if>
      </foreach>
    </where>
  </sql>
  <sql id="Base_Column_List">
    <!--
      WARNING - @mbg.generated
      This element is automatically generated by MyBatis Generator, do not modify.
    -->
    id, soft_ver_id, hard_ver_id, model_id, tel_type, tel_model, inner_ver, is_open, 
    des, up_ver_no, ser_ftp_id, per_timeout, per_max_vehicle, file_name, turn_off_flag
  </sql>
  <select id="selectByExample" parameterType="com.ccclubs.pub.orm.model.VerUpgradeExample" resultMap="BaseResultMap">
    <!--
      WARNING - @mbg.generated
      This element is automatically generated by MyBatis Generator, do not modify.
    -->
    select
    <if test="distinct">
      distinct
    </if>
    <include refid="Base_Column_List" />
    from ver_upgrade
    <if test="_parameter != null">
      <include refid="Example_Where_Clause" />
    </if>
    <if test="orderByClause != null">
      order by ${orderByClause}
    </if>
  </select>
  <select id="selectByPrimaryKey" parameterType="java.lang.Integer" resultMap="BaseResultMap">
    <!--
      WARNING - @mbg.generated
      This element is automatically generated by MyBatis Generator, do not modify.
    -->
    select 
    <include refid="Base_Column_List" />
    from ver_upgrade
    where id = #{id,jdbcType=INTEGER}
  </select>
  <delete id="deleteByPrimaryKey" parameterType="java.lang.Integer">
    <!--
      WARNING - @mbg.generated
      This element is automatically generated by MyBatis Generator, do not modify.
    -->
    delete from ver_upgrade
    where id = #{id,jdbcType=INTEGER}
  </delete>
  <delete id="deleteByExample" parameterType="com.ccclubs.pub.orm.model.VerUpgradeExample">
    <!--
      WARNING - @mbg.generated
      This element is automatically generated by MyBatis Generator, do not modify.
    -->
    delete from ver_upgrade
    <if test="_parameter != null">
      <include refid="Example_Where_Clause" />
    </if>
  </delete>
  <insert id="insert" parameterType="com.ccclubs.pub.orm.model.VerUpgrade">
    <!--
      WARNING - @mbg.generated
      This element is automatically generated by MyBatis Generator, do not modify.
    -->
    insert into ver_upgrade (id, soft_ver_id, hard_ver_id, 
      model_id, tel_type, tel_model, 
      inner_ver, is_open, des, 
      up_ver_no, ser_ftp_id, per_timeout, 
      per_max_vehicle, file_name, turn_off_flag
      )
    values (#{id,jdbcType=INTEGER}, #{softVerId,jdbcType=INTEGER}, #{hardVerId,jdbcType=INTEGER}, 
      #{modelId,jdbcType=INTEGER}, #{telType,jdbcType=INTEGER}, #{telModel,jdbcType=VARCHAR}, 
      #{innerVer,jdbcType=VARCHAR}, #{isOpen,jdbcType=TINYINT}, #{des,jdbcType=VARCHAR}, 
      #{upVerNo,jdbcType=VARCHAR}, #{serFtpId,jdbcType=INTEGER}, #{perTimeout,jdbcType=INTEGER}, 
      #{perMaxVehicle,jdbcType=INTEGER}, #{fileName,jdbcType=VARCHAR}, #{turnOffFlag,jdbcType=TINYINT}
      )
  </insert>
  <insert id="insertSelective" parameterType="com.ccclubs.pub.orm.model.VerUpgrade">
    <!--
      WARNING - @mbg.generated
      This element is automatically generated by MyBatis Generator, do not modify.
    -->
    insert into ver_upgrade
    <trim prefix="(" suffix=")" suffixOverrides=",">
      <if test="id != null">
        id,
      </if>
      <if test="softVerId != null">
        soft_ver_id,
      </if>
      <if test="hardVerId != null">
        hard_ver_id,
      </if>
      <if test="modelId != null">
        model_id,
      </if>
      <if test="telType != null">
        tel_type,
      </if>
      <if test="telModel != null">
        tel_model,
      </if>
      <if test="innerVer != null">
        inner_ver,
      </if>
      <if test="isOpen != null">
        is_open,
      </if>
      <if test="des != null">
        des,
      </if>
      <if test="upVerNo != null">
        up_ver_no,
      </if>
      <if test="serFtpId != null">
        ser_ftp_id,
      </if>
      <if test="perTimeout != null">
        per_timeout,
      </if>
      <if test="perMaxVehicle != null">
        per_max_vehicle,
      </if>
      <if test="fileName != null">
        file_name,
      </if>
      <if test="turnOffFlag != null">
        turn_off_flag,
      </if>
    </trim>
    <trim prefix="values (" suffix=")" suffixOverrides=",">
      <if test="id != null">
        #{id,jdbcType=INTEGER},
      </if>
      <if test="softVerId != null">
        #{softVerId,jdbcType=INTEGER},
      </if>
      <if test="hardVerId != null">
        #{hardVerId,jdbcType=INTEGER},
      </if>
      <if test="modelId != null">
        #{modelId,jdbcType=INTEGER},
      </if>
      <if test="telType != null">
        #{telType,jdbcType=INTEGER},
      </if>
      <if test="telModel != null">
        #{telModel,jdbcType=VARCHAR},
      </if>
      <if test="innerVer != null">
        #{innerVer,jdbcType=VARCHAR},
      </if>
      <if test="isOpen != null">
        #{isOpen,jdbcType=TINYINT},
      </if>
      <if test="des != null">
        #{des,jdbcType=VARCHAR},
      </if>
      <if test="upVerNo != null">
        #{upVerNo,jdbcType=VARCHAR},
      </if>
      <if test="serFtpId != null">
        #{serFtpId,jdbcType=INTEGER},
      </if>
      <if test="perTimeout != null">
        #{perTimeout,jdbcType=INTEGER},
      </if>
      <if test="perMaxVehicle != null">
        #{perMaxVehicle,jdbcType=INTEGER},
      </if>
      <if test="fileName != null">
        #{fileName,jdbcType=VARCHAR},
      </if>
      <if test="turnOffFlag != null">
        #{turnOffFlag,jdbcType=TINYINT},
      </if>
    </trim>
  </insert>
  <select id="countByExample" parameterType="com.ccclubs.pub.orm.model.VerUpgradeExample" resultType="java.lang.Long">
    <!--
      WARNING - @mbg.generated
      This element is automatically generated by MyBatis Generator, do not modify.
    -->
    select count(*) from ver_upgrade
    <if test="_parameter != null">
      <include refid="Example_Where_Clause" />
    </if>
  </select>
  <update id="updateByExampleSelective" parameterType="map">
    <!--
      WARNING - @mbg.generated
      This element is automatically generated by MyBatis Generator, do not modify.
    -->
    update ver_upgrade
    <set>
      <if test="record.id != null">
        id = #{record.id,jdbcType=INTEGER},
      </if>
      <if test="record.softVerId != null">
        soft_ver_id = #{record.softVerId,jdbcType=INTEGER},
      </if>
      <if test="record.hardVerId != null">
        hard_ver_id = #{record.hardVerId,jdbcType=INTEGER},
      </if>
      <if test="record.modelId != null">
        model_id = #{record.modelId,jdbcType=INTEGER},
      </if>
      <if test="record.telType != null">
        tel_type = #{record.telType,jdbcType=INTEGER},
      </if>
      <if test="record.telModel != null">
        tel_model = #{record.telModel,jdbcType=VARCHAR},
      </if>
      <if test="record.innerVer != null">
        inner_ver = #{record.innerVer,jdbcType=VARCHAR},
      </if>
      <if test="record.isOpen != null">
        is_open = #{record.isOpen,jdbcType=TINYINT},
      </if>
      <if test="record.des != null">
        des = #{record.des,jdbcType=VARCHAR},
      </if>
      <if test="record.upVerNo != null">
        up_ver_no = #{record.upVerNo,jdbcType=VARCHAR},
      </if>
      <if test="record.serFtpId != null">
        ser_ftp_id = #{record.serFtpId,jdbcType=INTEGER},
      </if>
      <if test="record.perTimeout != null">
        per_timeout = #{record.perTimeout,jdbcType=INTEGER},
      </if>
      <if test="record.perMaxVehicle != null">
        per_max_vehicle = #{record.perMaxVehicle,jdbcType=INTEGER},
      </if>
      <if test="record.fileName != null">
        file_name = #{record.fileName,jdbcType=VARCHAR},
      </if>
      <if test="record.turnOffFlag != null">
        turn_off_flag = #{record.turnOffFlag,jdbcType=TINYINT},
      </if>
    </set>
    <if test="_parameter != null">
      <include refid="Update_By_Example_Where_Clause" />
    </if>
  </update>
  <update id="updateByExample" parameterType="map">
    <!--
      WARNING - @mbg.generated
      This element is automatically generated by MyBatis Generator, do not modify.
    -->
    update ver_upgrade
    set id = #{record.id,jdbcType=INTEGER},
      soft_ver_id = #{record.softVerId,jdbcType=INTEGER},
      hard_ver_id = #{record.hardVerId,jdbcType=INTEGER},
      model_id = #{record.modelId,jdbcType=INTEGER},
      tel_type = #{record.telType,jdbcType=INTEGER},
      tel_model = #{record.telModel,jdbcType=VARCHAR},
      inner_ver = #{record.innerVer,jdbcType=VARCHAR},
      is_open = #{record.isOpen,jdbcType=TINYINT},
      des = #{record.des,jdbcType=VARCHAR},
      up_ver_no = #{record.upVerNo,jdbcType=VARCHAR},
      ser_ftp_id = #{record.serFtpId,jdbcType=INTEGER},
      per_timeout = #{record.perTimeout,jdbcType=INTEGER},
      per_max_vehicle = #{record.perMaxVehicle,jdbcType=INTEGER},
      file_name = #{record.fileName,jdbcType=VARCHAR},
      turn_off_flag = #{record.turnOffFlag,jdbcType=TINYINT}
    <if test="_parameter != null">
      <include refid="Update_By_Example_Where_Clause" />
    </if>
  </update>
  <update id="updateByPrimaryKeySelective" parameterType="com.ccclubs.pub.orm.model.VerUpgrade">
    <!--
      WARNING - @mbg.generated
      This element is automatically generated by MyBatis Generator, do not modify.
    -->
    update ver_upgrade
    <set>
      <if test="softVerId != null">
        soft_ver_id = #{softVerId,jdbcType=INTEGER},
      </if>
      <if test="hardVerId != null">
        hard_ver_id = #{hardVerId,jdbcType=INTEGER},
      </if>
      <if test="modelId != null">
        model_id = #{modelId,jdbcType=INTEGER},
      </if>
      <if test="telType != null">
        tel_type = #{telType,jdbcType=INTEGER},
      </if>
      <if test="telModel != null">
        tel_model = #{telModel,jdbcType=VARCHAR},
      </if>
      <if test="innerVer != null">
        inner_ver = #{innerVer,jdbcType=VARCHAR},
      </if>
      <if test="isOpen != null">
        is_open = #{isOpen,jdbcType=TINYINT},
      </if>
      <if test="des != null">
        des = #{des,jdbcType=VARCHAR},
      </if>
      <if test="upVerNo != null">
        up_ver_no = #{upVerNo,jdbcType=VARCHAR},
      </if>
      <if test="serFtpId != null">
        ser_ftp_id = #{serFtpId,jdbcType=INTEGER},
      </if>
      <if test="perTimeout != null">
        per_timeout = #{perTimeout,jdbcType=INTEGER},
      </if>
      <if test="perMaxVehicle != null">
        per_max_vehicle = #{perMaxVehicle,jdbcType=INTEGER},
      </if>
      <if test="fileName != null">
        file_name = #{fileName,jdbcType=VARCHAR},
      </if>
      <if test="turnOffFlag != null">
        turn_off_flag = #{turnOffFlag,jdbcType=TINYINT},
      </if>
    </set>
    where id = #{id,jdbcType=INTEGER}
  </update>
  <update id="updateByPrimaryKey" parameterType="com.ccclubs.pub.orm.model.VerUpgrade">
    <!--
      WARNING - @mbg.generated
      This element is automatically generated by MyBatis Generator, do not modify.
    -->
    update ver_upgrade
    set soft_ver_id = #{softVerId,jdbcType=INTEGER},
      hard_ver_id = #{hardVerId,jdbcType=INTEGER},
      model_id = #{modelId,jdbcType=INTEGER},
      tel_type = #{telType,jdbcType=INTEGER},
      tel_model = #{telModel,jdbcType=VARCHAR},
      inner_ver = #{innerVer,jdbcType=VARCHAR},
      is_open = #{isOpen,jdbcType=TINYINT},
      des = #{des,jdbcType=VARCHAR},
      up_ver_no = #{upVerNo,jdbcType=VARCHAR},
      ser_ftp_id = #{serFtpId,jdbcType=INTEGER},
      per_timeout = #{perTimeout,jdbcType=INTEGER},
      per_max_vehicle = #{perMaxVehicle,jdbcType=INTEGER},
      file_name = #{fileName,jdbcType=VARCHAR},
      turn_off_flag = #{turnOffFlag,jdbcType=TINYINT}
    where id = #{id,jdbcType=INTEGER}
  </update>
</mapper>